listcrunch/__init__.py
listcrunch/listcrunch.py
listcrunch/listcrunch_test.py
listcrunch-1.0.1.dist-info/LICENSE
listcrunch-1.0.1.dist-info/METADATA
listcrunch-1.0.1.dist-info/WHEEL
listcrunch-1.0.1.dist-info/top_level.txt
listcrunch-1.0.1.dist-info/RECORD
