Metadata-Version: 2.1
Name: listcrunch
Version: 1.0.1
Summary: A simple human-readable way to compress redundant sequential data
Home-page: https://github.com/MuckRock/listcrunch
Author: Dylan Freedman
Author-email: freedmand@gmail.com
License: UNKNOWN
Platform: UNKNOWN
Classifier: Programming Language :: Python :: 2
Classifier: Programming Language :: Python :: 3
Classifier: License :: OSI Approved :: MIT License
Classifier: Operating System :: OS Independent
